Workbook

Sheet Raw Data
A1: Row ID | B1: Order ID | C1: Order Date | D1: Ship Date | E1: Ship Mode | F1: Customer ID | G1: Customer Name | H1: Segment | I1: Country | J1: City | K1: State | L1: Postal Code | M1: Region | N1: Category | O1: Sub-Category | P1: Product Name | Q1: Sales | R1: Quantity | S1: Discount | T1: Profit | U1: Delivery Days | V1: Profit Margin
A2: 1 | B2: CA-2016-152156 | C2: 2016-11-08 | D2: 2016-11-11 | E2: Second Class | F2: CG-12520 | G2: Claire Gute | H2: Consumer | I2: United States | J2: Henderson | K2: Kentucky | L2: 42420 | M2: South | N2: Furniture | O2: Bookcases | P2: Bush Somerset Collection Bookcase | Q2: 261.96 | R2: 2 | S2: 0 | T2: 41.9136 | U2: =D2-C2 | V2: =IF(Q2=0,0,T2/Q2)
A3: 2 | B3: CA-2016-152156 | C3: 2016-11-08 | D3: 2016-11-11 | E3: Second Class | F3: CG-12520 | G3: Claire Gute | H3: Consumer | I3: United States | J3: Henderson | K3: Kentucky | L3: 42420 | M3: South | N3: Furniture | O3: Chairs | P3: Hon Deluxe Fabric Upholstered Stacking Chairs, Rounded Back | Q3: 731.94 | R3: 3 | S3: 0 | T3: 219.582 | U3: =D3-C3 | V3: =IF(Q3=0,0,T3/Q3)
A4: 3 | B4: CA-2016-138688 | C4: 2016-06-12 | D4: 2016-06-16 | E4: Second Class | F4: DV-13045 | G4: Darrin Van Huff | H4: Corporate | I4: United States | J4: Los Angeles | K4: California | L4: 90036 | M4: West | N4: Office Supplies | O4: Labels | P4: Self-Adhesive Address Labels for Typewriters by Universal | Q4: 14.62 | R4: 2 | S4: 0 | T4: 6.8714 | U4: =D4-C4 | V4: =IF(Q4=0,0,T4/Q4)
A5: 4 | B5: US-2015-108966 | C5: 2015-10-11 | D5: 2015-10-18 | E5: Standard Class | F5: SO-20335 | G5: Sean O'Donnell | H5: Consumer | I5: United States | J5: Fort Lauderdale | K5: Florida | L5: 33311 | M5: South | N5: Furniture | O5: Tables | P5: Bretford CR4500 Series Slim Rectangular Table | Q5: 957.5775 | R5: 5 | S5: 0.45 | T5: -383.031 | U5: =D5-C5 | V5: =IF(Q5=0,0,T5/Q5)
A6: 5 | B6: US-2015-108966 | C6: 2015-10-11 | D6: 2015-10-18 | E6: Standard Class | F6: SO-20335 | G6: Sean O'Donnell | H6: Consumer | I6: United States | J6: Fort Lauderdale | K6: Florida | L6: 33311 | M6: South | N6: Office Supplies | O6: Storage | P6: Eldon Fold 'N Roll Cart System | Q6: 22.368 | R6: 2 | S6: 0.2 | T6: 2.5164 | U6: =D6-C6 | V6: =IF(Q6=0,0,T6/Q6)
A7: 6 | B7: CA-2014-115812 | C7: 2014-06-09 | D7: 2014-06-14 | E7: Standard Class | F7: BH-11710 | G7: Brosina Hoffman | H7: Consumer | I7: United States | J7: Los Angeles | K7: California | L7: 90032 | M7: West | N7: Furniture | O7: Furnishings | P7: Eldon Expressions Wood and Plastic Desk Accessories, Cherry Wood | Q7: 48.86 | R7: 7 | S7: 0 | T7: 14.1694 | U7: =D7-C7 | V7: =IF(Q7=0,0,T7/Q7)
A8: 7 | B8: CA-2014-115812 | C8: 2014-06-09 | D8: 2014-06-14 | E8: Standard Class | F8: BH-11710 | G8: Brosina Hoffman | H8: Consumer | I8: United States | J8: Los Angeles | K8: California | L8: 90032 | M8: West | N8: Office Supplies | O8: Art | P8: Newell 322 | Q8: 7.28 | R8: 4 | S8: 0 | T8: 1.9656 | U8: =D8-C8 | V8: =IF(Q8=0,0,T8/Q8)
A9: 8 | B9: CA-2014-115812 | C9: 2014-06-09 | D9: 2014-06-14 | E9: Standard Class | F9: BH-11710 | G9: Brosina Hoffman | H9: Consumer | I9: United States | J9: Los Angeles | K9: California | L9: 90032 | M9: West | N9: Technology | O9: Phones | P9: Mitel 5320 IP Phone VoIP phone | Q9: 907.152 | R9: 6 | S9: 0.2 | T9: 90.7152 | U9: =D9-C9 | V9: =IF(Q9=0,0,T9/Q9)
A10: 9 | B10: CA-2014-115812 | C10: 2014-06-09 | D10: 2014-06-14 | E10: Standard Class | F10: BH-11710 | G10: Brosina Hoffman | H10: Consumer | I10: United States | J10: Los Angeles | K10: California | L10: 90032 | M10: West | N10: Office Supplies | O10: Binders | P10: DXL Angle-View Binders with Locking Rings by Samsill | Q10: 18.504 | R10: 3 | S10: 0.2 | T10: 5.7825 | U10: =D10-C10 | V10: =IF(Q10=0,0,T10/Q10)
A11: 10 | B11: CA-2014-115812 | C11: 2014-06-09 | D11: 2014-06-14 | E11: Standard Class | F11: BH-11710 | G11: Brosina Hoffman | H11: Consumer | I11: United States | J11: Los Angeles | K11: California | L11: 90032 | M11: West | N11: Office Supplies | O11: Appliances | P11: Belkin F5C206VTEL 6 Outlet Surge | Q11: 114.9 | R11: 5 | S11: 0 | T11: 34.47 | U11: =D11-C11 | V11: =IF(Q11=0,0,T11/Q11)
A12: 11 | B12: CA-2014-115812 | C12: 2014-06-09 | D12: 2014-06-14 | E12: Standard Class | F12: BH-11710 | G12: Brosina Hoffman | H12: Consumer | I12: United States | J12: Los Angeles | K12: California | L12: 90032 | M12: West | N12: Furniture | O12: Tables | P12: Chromcraft Rectangular Conference Tables | Q12: 1706.184 | R12: 9 | S12: 0.2 | T12: 85.3092 | U12: =D12-C12 | V12: =IF(Q12=0,0,T12/Q12)
A13: 12 | B13: CA-2014-115812 | C13: 2014-06-09 | D13: 2014-06-14 | E13: Standard Class | F13: BH-11710 | G13: Brosina Hoffman | H13: Consumer | I13: United States | J13: Los Angeles | K13: California | L13: 90032 | M13: West | N13: Technology | O13: Phones | P13: Konftel 250 Conference phone - Charcoal black | Q13: 911.424 | R13: 4 | S13: 0.2 | T13: 68.3568 | U13: =D13-C13 | V13: =IF(Q13=0,0,T13/Q13)
... A9995: 9994 | B9995: CA-2017-119914 | C9995: 2017-05-04 | D9995: 2017-05-09 | E9995: Second Class | F9995: CC-12220 | G9995: Chris Cortes | H9995: Consumer | I9995: United States | J9995: Westminster | K9995: California | L9995: 92683 | M9995: West | N9995: Office Supplies | O9995: Appliances | P9995: Acco 7-Outlet Masterpiece Power Center, Wihtout Fax/Phone Line Protection | Q9995: 243.16 | R9995: 2 | S9995: 0 | T9995: 72.948 | U9995: =D9995-C9995 | V9995: =IF(Q9995=0,0,T9995/Q9995)

Sheet Summary Statistics
A1: Descriptive Statistics — All Values Computed via Excel Formulas
A3: Statistic | B3: Sales ($) | C3: Profit ($) | D3: Quantity | E3: Discount | F3: Delivery Days
A4: Count | B4: =COUNT('Raw Data'!Q2:Q9995) | C4: =COUNT('Raw Data'!T2:T9995) | D4: =COUNT('Raw Data'!R2:R9995) | E4: =COUNT('Raw Data'!S2:S9995) | F4: =COUNT('Raw Data'!U2:U9995)
A5: Sum | B5: =SUM('Raw Data'!Q2:Q9995) | C5: =SUM('Raw Data'!T2:T9995) | D5: =SUM('Raw Data'!R2:R9995) | E5: =SUM('Raw Data'!S2:S9995) | F5: =SUM('Raw Data'!U2:U9995)
A6: Mean | B6: =AVERAGE('Raw Data'!Q2:Q9995) | C6: =AVERAGE('Raw Data'!T2:T9995) | D6: =AVERAGE('Raw Data'!R2:R9995) | E6: =AVERAGE('Raw Data'!S2:S9995) | F6: =AVERAGE('Raw Data'!U2:U9995)
A7: Median | B7: =MEDIAN('Raw Data'!Q2:Q9995) | C7: =MEDIAN('Raw Data'!T2:T9995) | D7: =MEDIAN('Raw Data'!R2:R9995) | E7: =MEDIAN('Raw Data'!S2:S9995) | F7: =MEDIAN('Raw Data'!U2:U9995)
A8: Std Deviation | B8: =STDEV('Raw Data'!Q2:Q9995) | C8: =STDEV('Raw Data'!T2:T9995) | D8: =STDEV('Raw Data'!R2:R9995) | E8: =STDEV('Raw Data'!S2:S9995) | F8: =STDEV('Raw Data'!U2:U9995)
A9: Min | B9: =MIN('Raw Data'!Q2:Q9995) | C9: =MIN('Raw Data'!T2:T9995) | D9: =MIN('Raw Data'!R2:R9995) | E9: =MIN('Raw Data'!S2:S9995) | F9: =MIN('Raw Data'!U2:U9995)
A10: Max | B10: =MAX('Raw Data'!Q2:Q9995) | C10: =MAX('Raw Data'!T2:T9995) | D10: =MAX('Raw Data'!R2:R9995) | E10: =MAX('Raw Data'!S2:S9995) | F10: =MAX('Raw Data'!U2:U9995)
A11: Q1 (25th Pctl) | B11: =PERCENTILE('Raw Data'!Q2:Q9995,0.25) | C11: =PERCENTILE('Raw Data'!T2:T9995,0.25) | D11: =PERCENTILE('Raw Data'!R2:R9995,0.25) | E11: =PERCENTILE('Raw Data'!S2:S9995,0.25) | F11: =PERCENTILE('Raw Data'!U2:U9995,0.25)
A12: Q3 (75th Pctl) | B12: =PERCENTILE('Raw Data'!Q2:Q9995,0.75) | C12: =PERCENTILE('Raw Data'!T2:T9995,0.75) | D12: =PERCENTILE('Raw Data'!R2:R9995,0.75) | E12: =PERCENTILE('Raw Data'!S2:S9995,0.75) | F12: =PERCENTILE('Raw Data'!U2:U9995,0.75)
A13: Variance | B13: =VAR('Raw Data'!Q2:Q9995) | C13: =VAR('Raw Data'!T2:T9995) | D13: =VAR('Raw Data'!R2:R9995) | E13: =VAR('Raw Data'!S2:S9995) | F13: =VAR('Raw Data'!U2:U9995)
A14: IQR (Q3 - Q1) | B14: =B11-B10 | C14: =C11-C10 | D14: =D11-D10 | E14: =E11-E10 | F14: =F11-F10
A17: Performance by Customer Segment
A19: Segment | B19: Total Sales | C19: Total Profit | D19: Profit Margin | E19: Order Count
A20: Consumer | B20: =SUMIF('Raw Data'!H2:H9995,A20,'Raw Data'!Q2:Q9995) | C20: =SUMIF('Raw Data'!H2:H9995,A20,'Raw Data'!T2:T9995) | D20: =IF(B20=0,0,C20/B20) | E20: =COUNTIF('Raw Data'!H2:H9995,A20)
A21: Corporate | B21: =SUMIF('Raw Data'!H2:H9995,A21,'Raw Data'!Q2:Q9995) | C21: =SUMIF('Raw Data'!H2:H9995,A21,'Raw Data'!T2:T9995) | D21: =IF(B21=0,0,C21/B21) | E21: =COUNTIF('Raw Data'!H2:H9995,A21)
A22: Home Office | B22: =SUMIF('Raw Data'!H2:H9995,A22,'Raw Data'!Q2:Q9995) | C22: =SUMIF('Raw Data'!H2:H9995,A22,'Raw Data'!T2:T9995) | D22: =IF(B22=0,0,C22/B22) | E22: =COUNTIF('Raw Data'!H2:H9995,A22)
A23: TOTAL | B23: =SUM(B20:B22) | C23: =SUM(C20:C22) | D23: =IF(B23=0,0,C23/B23) | E23: =SUM(E20:E22)

Sheet Revenue Analysis
A1: Revenue Trend Analysis
A3: Year | B3: Total Revenue | C3: Total Profit | D3: Total Orders | E3: Avg Order Value | F3: Profit Margin | G3: YoY Growth
A4: 2014 | B4: =SUMPRODUCT((LEFT('Raw Data'!C2:C9995,4)=TEXT(A4,"0000"))*'Raw Data'!Q2:Q9995) | C4: =SUMPRODUCT((LEFT('Raw Data'!C2:C9995,4)=TEXT(A4,"0000"))*'Raw Data'!T2:T9995) | D4: =SUMPRODUCT((LEFT('Raw Data'!C2:C9995,4)=TEXT(A4,"0000"))*1) | E4: =IF(D4=0,0,B4/D4) | F4: =IF(B4=0,0,C4/B4) | G4: N/A
A5: 2015 | B5: =SUMPRODUCT((LEFT('Raw Data'!C2:C9995,4)=TEXT(A5,"0000"))*'Raw Data'!Q2:Q9995) | C5: =SUMPRODUCT((LEFT('Raw Data'!C2:C9995,4)=TEXT(A5,"0000"))*'Raw Data'!T2:T9995) | D5: =SUMPRODUCT((LEFT('Raw Data'!C2:C9995,4)=TEXT(A5,"0000"))*1) | E5: =IF(D5=0,0,B5/D5) | F5: =IF(B5=0,0,C5/B5) | G5: =IF(B4=0,0,(B5-B4)/B4)
A6: 2016 | B6: =SUMPRODUCT((LEFT('Raw Data'!C2:C9995,4)=TEXT(A6,"0000"))*'Raw Data'!Q2:Q9995) | C6: =SUMPRODUCT((LEFT('Raw Data'!C2:C9995,4)=TEXT(A6,"0000"))*'Raw Data'!T2:T9995) | D6: =SUMPRODUCT((LEFT('Raw Data'!C2:C9995,4)=TEXT(A6,"0000"))*1) | E6: =IF(D6=0,0,B6/D6) | F6: =IF(B6=0,0,C6/B6) | G6: =IF(B5=0,0,(B6-B5)/B5)
A7: 2017 | B7: =SUMPRODUCT((LEFT('Raw Data'!C2:C9995,4)=TEXT(A7,"0000"))*'Raw Data'!Q2:Q9995) | C7: =SUMPRODUCT((LEFT('Raw Data'!C2:C9995,4)=TEXT(A7,"0000"))*'Raw Data'!T2:T9995) | D7: =SUMPRODUCT((LEFT('Raw Data'!C2:C9995,4)=TEXT(A7,"0000"))*1) | E7: =IF(D7=0,0,B7/D7) | F7: =IF(B7=0,0,C7/B7) | G7: =IF(B6=0,0,(B7-B6)/B6)
A8: TOTAL | B8: =SUM(B4:B7) | C8: =SUM(C4:C7) | D8: =SUM(D4:D7) | E8: =IF(D8=0,0,B8/D8) | F8: =IF(B8=0,0,C8/B8)
A39: Monthly Revenue Breakdown
A41: Year | B41: Jan | C41: Feb | D41: Mar | E41: Apr | F41: May | G41: Jun | H41: Jul | I41: Aug | J41: Sep | K41: Oct | L41: Nov | M41: Dec | N41: Year Total
A42: 2014 | B42: 14236.9 | C42: 4519.89 | D42: 55691.01 | E42: 28295.34 | F42: 23648.29 | G42: 34595.13 | H42: 33946.39 | I42: 27909.47 | J42: 81777.35 | K42: 31453.39 | L42: 78628.72 | M42: 69545.62 | N42: =SUM(B42:M42)
A43: 2015 | B43: 18174.08 | C43: 11951.41 | D43: 38726.25 | E43: 34195.21 | F43: 30131.69 | G43: 24797.29 | H43: 28765.32 | I43: 36898.33 | J43: 64595.92 | K43: 31404.92 | L43: 75972.56 | M43: 74919.52 | N43: =SUM(B43:M43)
A44: 2016 | B44: 18542.49 | C44: 22978.82 | D44: 51715.88 | E44: 38750.04 | F44: 56987.73 | G44: 40344.53 | H44: 39261.96 | I44: 31115.37 | J44: 73410.02 | K44: 59687.74 | L44: 79411.97 | M44: 96999.04 | N44: =SUM(B44:M44)
A45: 2017 | B45: 43971.37 | C45: 20301.13 | D45: 58872.35 | E45: 36521.54 | F45: 44261.11 | G45: 52981.73 | H45: 45264.42 | I45: 63120.89 | J45: 87866.65 | K45: 77776.92 | L45: 118447.82 | M45: 83829.32 | N45: =SUM(B45:M45)

Sheet Profitability Analysis
A1: Profitability Analysis
A3: By Category
A5: Category | B5: Total Sales | C5: Total Profit | D5: Profit Margin | E5: Units Sold
A6: Technology | B6: =SUMIF('Raw Data'!N2:N9995,A6,'Raw Data'!Q2:Q9995) | C6: =SUMIF('Raw Data'!N2:N9995,A6,'Raw Data'!T2:T9995) | D6: =IF(B6=0,0,C6/B6) | E6: =SUMIF('Raw Data'!N2:N9995,A6,'Raw Data'!R2:R9995)
A7: Furniture | B7: =SUMIF('Raw Data'!N2:N9995,A7,'Raw Data'!Q2:Q9995) | C7: =SUMIF('Raw Data'!N2:N9995,A7,'Raw Data'!T2:T9995) | D7: =IF(B7=0,0,C7/B7) | E7: =SUMIF('Raw Data'!N2:N9995,A7,'Raw Data'!R2:R9995)
A8: Office Supplies | B8: =SUMIF('Raw Data'!N2:N9995,A8,'Raw Data'!Q2:Q9995) | C8: =SUMIF('Raw Data'!N2:N9995,A8,'Raw Data'!T2:T9995) | D8: =IF(B8=0,0,C8/B8) | E8: =SUMIF('Raw Data'!N2:N9995,A8,'Raw Data'!R2:R9995)
A9: TOTAL | B9: =SUM(B6:B8) | C9: =SUM(C6:C8) | D9: =IF(B9=0,0,C9/B9) | E9: =SUM(E6:E8)
A37: By Sub-Category
A39: Sub-Category | B39: Total Sales | C39: Total Profit | D39: Profit Margin
A40: Accessories | B40: =SUMIF('Raw Data'!O2:O9995,A40,'Raw Data'!Q2:Q9995) | C40: =SUMIF('Raw Data'!O2:O9995,A40,'Raw Data'!T2:T9995) | D40: =IF(B40=0,0,C40/B40)
A41: Appliances | B41: =SUMIF('Raw Data'!O2:O9995,A41,'Raw Data'!Q2:Q9995) | C41: =SUMIF('Raw Data'!O2:O9995,A41,'Raw Data'!T2:T9995) | D41: =IF(B41=0,0,C41/B41)
A42: Art | B42: =SUMIF('Raw Data'!O2:O9995,A42,'Raw Data'!Q2:Q9995) | C42: =SUMIF('Raw Data'!O2:O9995,A42,'Raw Data'!T2:T9995) | D42: =IF(B42=0,0,C42/B42)
A43: Binders | B43: =SUMIF('Raw Data'!O2:O9995,A43,'Raw Data'!Q2:Q9995) | C43: =SUMIF('Raw Data'!O2:O9995,A43,'Raw Data'!T2:T9995) | D43: =IF(B43=0,0,C43/B43)
A44: Bookcases | B44: =SUMIF('Raw Data'!O2:O9995,A44,'Raw Data'!Q2:Q9995) | C44: =SUMIF('Raw Data'!O2:O9995,A44,'Raw Data'!T2:T9995) | D44: =IF(B44=0,0,C44/B44)
A45: Chairs | B45: =SUMIF('Raw Data'!O2:O9995,A45,'Raw Data'!Q2:Q9995) | C45: =SUMIF('Raw Data'!O2:O9995,A45,'Raw Data'!T2:T9995) | D45: =IF(B45=0,0,C45/B45)
A46: Copiers | B46: =SUMIF('Raw Data'!O2:O9995,A46,'Raw Data'!Q2:Q9995) | C46: =SUMIF('Raw Data'!O2:O9995,A46,'Raw Data'!T2:T9995) | D46: =IF(B46=0,0,C46/B46)
A47: Envelopes | B47: =SUMIF('Raw Data'!O2:O9995,A47,'Raw Data'!Q2:Q9995) | C47: =SUMIF('Raw Data'!O2:O9995,A47,'Raw Data'!T2:T9995) | D47: =IF(B47=0,0,C47/B47)
A48: Fasteners | B48: =SUMIF('Raw Data'!O2:O9995,A48,'Raw Data'!Q2:Q9995) | C48: =SUMIF('Raw Data'!O2:O9995,A48,'Raw Data'!T2:T9995) | D48: =IF(B48=0,0,C48/B48)
A49: Furnishings | B49: =SUMIF('Raw Data'!O2:O9995,A49,'Raw Data'!Q2:Q9995) | C49: =SUMIF('Raw Data'!O2:O9995,A49,'Raw Data'!T2:T9995) | D49: =IF(B49=0,0,C49/B49)
A50: Labels | B50: =SUMIF('Raw Data'!O2:O9995,A50,'Raw Data'!Q2:Q9995) | C50: =SUMIF('Raw Data'!O2:O9995,A50,'Raw Data'!T2:T9995) | D50: =IF(B50=0,0,C50/B50)
A51: Machines | B51: =SUMIF('Raw Data'!O2:O9995,A51,'Raw Data'!Q2:Q9995) | C51: =SUMIF('Raw Data'!O2:O9995,A51,'Raw Data'!T2:T9995) | D51: =IF(B51=0,0,C51/B51)
A52: Paper | B52: =SUMIF('Raw Data'!O2:O9995,A52,'Raw Data'!Q2:Q9995) | C52: =SUMIF('Raw Data'!O2:O9995,A52,'Raw Data'!T2:T9995) | D52: =IF(B52=0,0,C52/B52)
A53: Phones | B53: =SUMIF('Raw Data'!O2:O9995,A53,'Raw Data'!Q2:Q9995) | C53: =SUMIF('Raw Data'!O2:O9995,A53,'Raw Data'!T2:T9995) | D53: =IF(B53=0,0,C53/B53)
A54: Storage | B54: =SUMIF('Raw Data'!O2:O9995,A54,'Raw Data'!Q2:Q9995) | C54: =SUMIF('Raw Data'!O2:O9995,A54,'Raw Data'!T2:T9995) | D54: =IF(B54=0,0,C54/B54)
A55: Supplies | B55: =SUMIF('Raw Data'!O2:O9995,A55,'Raw Data'!Q2:Q9995) | C55: =SUMIF('Raw Data'!O2:O9995,A55,'Raw Data'!T2:T9995) | D55: =IF(B55=0,0,C55/B55)
A56: Tables | B56: =SUMIF('Raw Data'!O2:O9995,A56,'Raw Data'!Q2:Q9995) | C56: =SUMIF('Raw Data'!O2:O9995,A56,'Raw Data'!T2:T9995) | D56: =IF(B56=0,0,C56/B56)

Sheet Customer Segmentation
A1: RFM Customer Segmentation Analysis
A2: All scores computed via Excel formulas (PERCENTRANK, IF). Click any cell to verify.
A4: Customer ID | B4: Customer Name | C4: Recency (days) | D4: Frequency | E4: Monetary ($) | F4: R Score | G4: F Score | H4: M Score | I4: RFM Score | J4: Segment
A5: SM-20320 | B5: Sean Miller | C5: 79 | D5: 5 | E5: 25043.05 | F5: =IF(PERCENTRANK($C$5:$C$797,C5)<=0.25,4,IF(PERCENTRANK($C$5:$C$797,C5)<=0.5,3,IF(PERCENTRANK($C$5:$C$797,C5)<=0.75,2,1))) | G5: =IF(PERCENTRANK($D$5:$D$797,D5)>=0.75,4,IF(PERCENTRANK($D$5:$D$797,D5)>=0.5,3,IF(PERCENTRANK($D$5:$D$797,D5)>=0.25,2,1))) | H5: =IF(PERCENTRANK($E$5:$E$797,E5)>=0.75,4,IF(PERCENTRANK($E$5:$E$797,E5)>=0.5,3,IF(PERCENTRANK($E$5:$E$797,E5)>=0.25,2,1))) | I5: =F5+G5+H5 | J5: =IF(I5>=10,"Champions",IF(I5>=8,"Loyal Customers",IF(I5>=6,"Potential Loyalists",IF(I5>=4,"At Risk","Lost"))))
A6: TC-20980 | B6: Tamara Chand | C6: 399 | D6: 5 | E6: 19052.22 | F6: =IF(PERCENTRANK($C$5:$C$797,C6)<=0.25,4,IF(PERCENTRANK($C$5:$C$797,C6)<=0.5,3,IF(PERCENTRANK($C$5:$C$797,C6)<=0.75,2,1))) | G6: =IF(PERCENTRANK($D$5:$D$797,D6)>=0.75,4,IF(PERCENTRANK($D$5:$D$797,D6)>=0.5,3,IF(PERCENTRANK($D$5:$D$797,D6)>=0.25,2,1))) | H6: =IF(PERCENTRANK($E$5:$E$797,E6)>=0.75,4,IF(PERCENTRANK($E$5:$E$797,E6)>=0.5,3,IF(PERCENTRANK($E$5:$E$797,E6)>=0.25,2,1))) | I6: =F6+G6+H6 | J6: =IF(I6>=10,"Champions",IF(I6>=8,"Loyal Customers",IF(I6>=6,"Potential Loyalists",IF(I6>=4,"At Risk","Lost"))))
A7: RB-19360 | B7: Raymond Buch | C7: 96 | D7: 6 | E7: 15117.34 | F7: =IF(PERCENTRANK($C$5:$C$797,C7)<=0.25,4,IF(PERCENTRANK($C$5:$C$797,C7)<=0.5,3,IF(PERCENTRANK($C$5:$C$797,C7)<=0.75,2,1))) | G7: =IF(PERCENTRANK($D$5:$D$797,D7)>=0.75,4,IF(PERCENTRANK($D$5:$D$797,D7)>=0.5,3,IF(PERCENTRANK($D$5:$D$797,D7)>=0.25,2,1))) | H7: =IF(PERCENTRANK($E$5:$E$797,E7)>=0.75,4,IF(PERCENTRANK($E$5:$E$797,E7)>=0.5,3,IF(PERCENTRANK($E$5:$E$797,E7)>=0.25,2,1))) | I7: =F7+G7+H7 | J7: =IF(I7>=10,"Champions",IF(I7>=8,"Loyal Customers",IF(I7>=6,"Potential Loyalists",IF(I7>=4,"At Risk","Lost"))))
A8: TA-21385 | B8: Tom Ashbrook | C8: 69 | D8: 4 | E8: 14595.62 | F8: =IF(PERCENTRANK($C$5:$C$797,C8)<=0.25,4,IF(PERCENTRANK($C$5:$C$797,C8)<=0.5,3,IF(PERCENTRANK($C$5:$C$797,C8)<=0.75,2,1))) | G8: =IF(PERCENTRANK($D$5:$D$797,D8)>=0.75,4,IF(PERCENTRANK($D$5:$D$797,D8)>=0.5,3,IF(PERCENTRANK($D$5:$D$797,D8)>=0.25,2,1))) | H8: =IF(PERCENTRANK($E$5:$E$797,E8)>=0.75,4,IF(PERCENTRANK($E$5:$E$797,E8)>=0.5,3,IF(PERCENTRANK($E$5:$E$797,E8)>=0.25,2,1))) | I8: =F8+G8+H8 | J8: =IF(I8>=10,"Champions",IF(I8>=8,"Loyal Customers",IF(I8>=6,"Potential Loyalists",IF(I8>=4,"At Risk","Lost"))))
A9: AB-10105 | B9: Adrian Barton | C9: 41 | D9: 10 | E9: 14473.57 | F9: =IF(PERCENTRANK($C$5:$C$797,C9)<=0.25,4,IF(PERCENTRANK($C$5:$C$797,C9)<=0.5,3,IF(PERCENTRANK($C$5:$C$797,C9)<=0.75,2,1))) | G9: =IF(PERCENTRANK($D$5:$D$797,D9)>=0.75,4,IF(PERCENTRANK($D$5:$D$797,D9)>=0.5,3,IF(PERCENTRANK($D$5:$D$797,D9)>=0.25,2,1))) | H9: =IF(PERCENTRANK($E$5:$E$797,E9)>=0.75,4,IF(PERCENTRANK($E$5:$E$797,E9)>=0.5,3,IF(PERCENTRANK($E$5:$E$797,E9)>=0.25,2,1))) | I9: =F9+G9+H9 | J9: =IF(I9>=10,"Champions",IF(I9>=8,"Loyal Customers",IF(I9>=6,"Potential Loyalists",IF(I9>=4,"At Risk","Lost"))))
A10: KL-16645 | B10: Ken Lonsdale | C10: 47 | D10: 12 | E10: 14175.23 | F10: =IF(PERCENTRANK($C$5:$C$797,C10)<=0.25,4,IF(PERCENTRANK($C$5:$C$797,C10)<=0.5,3,IF(PERCENTRANK($C$5:$C$797,C10)<=0.75,2,1))) | G10: =IF(PERCENTRANK($D$5:$D$797,D10)>=0.75,4,IF(PERCENTRANK($D$5:$D$797,D10)>=0.5,3,IF(PERCENTRANK($D$5:$D$797,D10)>=0.25,2,1))) | H10: =IF(PERCENTRANK($E$5:$E$797,E10)>=0.75,4,IF(PERCENTRANK($E$5:$E$797,E10)>=0.5,3,IF(PERCENTRANK($E$5:$E$797,E10)>=0.25,2,1))) | I10: =F10+G10+H10 | J10: =IF(I10>=10,"Champions",IF(I10>=8,"Loyal Customers",IF(I10>=6,"Potential Loyalists",IF(I10>=4,"At Risk","Lost"))))
A11: SC-20095 | B11: Sanjit Chand | C11: 349 | D11: 9 | E11: 14142.33 | F11: =IF(PERCENTRANK($C$5:$C$797,C11)<=0.25,4,IF(PERCENTRANK($C$5:$C$797,C11)<=0.5,3,IF(PERCENTRANK($C$5:$C$797,C11)<=0.75,2,1))) | G11: =IF(PERCENTRANK($D$5:$D$797,D11)>=0.75,4,IF(PERCENTRANK($D$5:$D$797,D11)>=0.5,3,IF(PERCENTRANK($D$5:$D$797,D11)>=0.25,2,1))) | H11: =IF(PERCENTRANK($E$5:$E$797,E11)>=0.75,4,IF(PERCENTRANK($E$5:$E$797,E11)>=0.5,3,IF(PERCENTRANK($E$5:$E$797,E11)>=0.25,2,1))) | I11: =F11+G11+H11 | J11: =IF(I11>=10,"Champions",IF(I11>=8,"Loyal Customers",IF(I11>=6,"Potential Loyalists",IF(I11>=4,"At Risk","Lost"))))
A12: HL-15040 | B12: Hunter Lopez | C12: 43 | D12: 6 | E12: 12873.3 | F12: =IF(PERCENTRANK($C$5:$C$797,C12)<=0.25,4,IF(PERCENTRANK($C$5:$C$797,C12)<=0.5,3,IF(PERCENTRANK($C$5:$C$797,C12)<=0.75,2,1))) | G12: =IF(PERCENTRANK($D$5:$D$797,D12)>=0.75,4,IF(PERCENTRANK($D$5:$D$797,D12)>=0.5,3,IF(PERCENTRANK($D$5:$D$797,D12)>=0.25,2,1))) | H12: =IF(PERCENTRANK($E$5:$E$797,E12)>=0.75,4,IF(PERCENTRANK($E$5:$E$797,E12)>=0.5,3,IF(PERCENTRANK($E$5:$E$797,E12)>=0.25,2,1))) | I12: =F12+G12+H12 | J12: =IF(I12>=10,"Champions",IF(I12>=8,"Loyal Customers",IF(I12>=6,"Potential Loyalists",IF(I12>=4,"At Risk","Lost"))))
A13: SE-20110 | B13: Sanjit Engle | C13: 9 | D13: 11 | E13: 12209.44 | F13: =IF(PERCENTRANK($C$5:$C$797,C13)<=0.25,4,IF(PERCENTRANK($C$5:$C$797,C13)<=0.5,3,IF(PERCENTRANK($C$5:$C$797,C13)<=0.75,2,1))) | G13: =IF(PERCENTRANK($D$5:$D$797,D13)>=0.75,4,IF(PERCENTRANK($D$5:$D$797,D13)>=0.5,3,IF(PERCENTRANK($D$5:$D$797,D13)>=0.25,2,1))) | H13: =IF(PERCENTRANK($E$5:$E$797,E13)>=0.75,4,IF(PERCENTRANK($E$5:$E$797,E13)>=0.5,3,IF(PERCENTRANK($E$5:$E$797,E13)>=0.25,2,1))) | I13: =F13+G13+H13 | J13: =IF(I13>=10,"Champions",IF(I13>=8,"Loyal Customers",IF(I13>=6,"Potential Loyalists",IF(I13>=4,"At Risk","Lost"))))
A14: CC-12370 | B14: Christopher Conant | C14: 43 | D14: 5 | E14: 12129.07 | F14: =IF(PERCENTRANK($C$5:$C$797,C14)<=0.25,4,IF(PERCENTRANK($C$5:$C$797,C14)<=0.5,3,IF(PERCENTRANK($C$5:$C$797,C14)<=0.75,2,1))) | G14: =IF(PERCENTRANK($D$5:$D$797,D14)>=0.75,4,IF(PERCENTRANK($D$5:$D$797,D14)>=0.5,3,IF(PERCENTRANK($D$5:$D$797,D14)>=0.25,2,1))) | H14: =IF(PERCENTRANK($E$5:$E$797,E14)>=0.75,4,IF(PERCENTRANK($E$5:$E$797,E14)>=0.5,3,IF(PERCENTRANK($E$5:$E$797,E14)>=0.25,2,1))) | I14: =F14+G14+H14 | J14: =IF(I14>=10,"Champions",IF(I14>=8,"Loyal Customers",IF(I14>=6,"Potential Loyalists",IF(I14>=4,"At Risk","Lost"))))
A15: TS-21370 | B15: Todd Sumrall | C15: 36 | D15: 6 | E15: 11891.75 | F15: =IF(PERCENTRANK($C$5:$C$797,C15)<=0.25,4,IF(PERCENTRANK($C$5:$C$797,C15)<=0.5,3,IF(PERCENTRANK($C$5:$C$797,C15)<=0.75,2,1))) | G15: =IF(PERCENTRANK($D$5:$D$797,D15)>=0.75,4,IF(PERCENTRANK($D$5:$D$797,D15)>=0.5,3,IF(PERCENTRANK($D$5:$D$797,D15)>=0.25,2,1))) | H15: =IF(PERCENTRANK($E$5:$E$797,E15)>=0.75,4,IF(PERCENTRANK($E$5:$E$797,E15)>=0.5,3,IF(PERCENTRANK($E$5:$E$797,E15)>=0.25,2,1))) | I15: =F15+G15+H15 | J15: =IF(I15>=10,"Champions",IF(I15>=8,"Loyal Customers",IF(I15>=6,"Potential Loyalists",IF(I15>=4,"At Risk","Lost"))))
A16: GT-14710 | B16: Greg Tran | C16: 36 | D16: 11 | E16: 11820.12 | F16: =IF(PERCENTRANK($C$5:$C$797,C16)<=0.25,4,IF(PERCENTRANK($C$5:$C$797,C16)<=0.5,3,IF(PERCENTRANK($C$5:$C$797,C16)<=0.75,2,1))) | G16: =IF(PERCENTRANK($D$5:$D$797,D16)>=0.75,4,IF(PERCENTRANK($D$5:$D$797,D16)>=0.5,3,IF(PERCENTRANK($D$5:$D$797,D16)>=0.25,2,1))) | H16: =IF(PERCENTRANK($E$5:$E$797,E16)>=0.75,4,IF(PERCENTRANK($E$5:$E$797,E16)>=0.5,3,IF(PERCENTRANK($E$5:$E$797,E16)>=0.25,2,1))) | I16: =F16+G16+H16 | J16: =IF(I16>=10,"Champions",IF(I16>=8,"Loyal Customers",IF(I16>=6,"Potential Loyalists",IF(I16>=4,"At Risk","Lost"))))
... A797: TS-21085 | B797: Thais Sissman | C797: 357 | D797: 2 | E797: 4.83 | F797: =IF(PERCENTRANK($C$5:$C$797,C797)<=0.25,4,IF(PERCENTRANK($C$5:$C$797,C797)<=0.5,3,IF(PERCENTRANK($C$5:$C$797,C797)<=0.75,2,1))) | G797: =IF(PERCENTRANK($D$5:$D$797,D797)>=0.75,4,IF(PERCENTRANK($D$5:$D$797,D797)>=0.5,3,IF(PERCENTRANK($D$5:$D$797,D797)>=0.25,2,1))) | H797: =IF(PERCENTRANK($E$5:$E$797,E797)>=0.75,4,IF(PERCENTRANK($E$5:$E$797,E797)>=0.5,3,IF(PERCENTRANK($E$5:$E$797,E797)>=0.25,2,1))) | I797: =F797+G797+H797 | J797: =IF(I797>=10,"Champions",IF(I797>=8,"Loyal Customers",IF(I797>=6,"Potential Loyalists",IF(I797>=4,"At Risk","Lost"))))
A800: Segment Summary
A802: Segment | B802: Customer Count | C802: % of Customers | D802: Total Revenue | E802: Avg Revenue/Customer
A803: Champions | B803: =COUNTIF(J5:J797,A803) | C803: =IF(SUM(B803:B807)=0,0,B803/SUM(B803:B807)) | D803: =SUMIF(J5:J797,A803,E5:E797) | E803: =IF(B803=0,0,D803/B803)
A804: Loyal Customers | B804: =COUNTIF(J5:J797,A804) | C804: =IF(SUM(B803:B807)=0,0,B804/SUM(B803:B807)) | D804: =SUMIF(J5:J797,A804,E5:E797) | E804: =IF(B804=0,0,D804/B804)
A805: Potential Loyalists | B805: =COUNTIF(J5:J797,A805) | C805: =IF(SUM(B803:B807)=0,0,B805/SUM(B803:B807)) | D805: =SUMIF(J5:J797,A805,E5:E797) | E805: =IF(B805=0,0,D805/B805)
A806: At Risk | B806: =COUNTIF(J5:J797,A806) | C806: =IF(SUM(B803:B807)=0,0,B806/SUM(B803:B807)) | D806: =SUMIF(J5:J797,A806,E5:E797) | E806: =IF(B806=0,0,D806/B806)
A807: Lost | B807: =COUNTIF(J5:J797,A807) | C807: =IF(SUM(B803:B807)=0,0,B807/SUM(B803:B807)) | D807: =SUMIF(J5:J797,A807,E5:E797) | E807: =IF(B807=0,0,D807/B807)
A808: TOTAL | B808: =SUM(B803:B807) | D808: =SUM(D803:D807)

Sheet Product Performance
A1: Product Performance Analysis
A3: Top 20 Products by Revenue
A5: Rank | B5: Product Name | C5: Total Sales | D5: Total Profit | E5: Profit Margin | F5: Units Sold
A6: 1 | B6: Canon imageCLASS 2200 Advanced Copier | C6: 61599.82 | D6: 25199.93 | E6: =IF(C6=0,0,D6/C6) | F6: 20
A7: 2 | B7: Fellowes PB500 Electric Punch Plastic Comb Binding Machine with M | C7: 27453.38 | D7: 7753.04 | E7: =IF(C7=0,0,D7/C7) | F7: 31
A8: 3 | B8: Cisco TelePresence System EX90 Videoconferencing Unit | C8: 22638.48 | D8: -1811.08 | E8: =IF(C8=0,0,D8/C8) | F8: 6
A9: 4 | B9: HON 5400 Series Task Chairs for Big and Tall | C9: 21870.58 | D9: 0 | E9: =IF(C9=0,0,D9/C9) | F9: 39
A10: 5 | B10: GBC DocuBind TL300 Electric Binding System | C10: 19823.48 | D10: 2233.51 | E10: =IF(C10=0,0,D10/C10) | F10: 37
A11: 6 | B11: GBC Ibimaster 500 Manual ProClick Binding System | C11: 19024.5 | D11: 760.98 | E11: =IF(C11=0,0,D11/C11) | F11: 48
A12: 7 | B12: Hewlett Packard LaserJet 3310 Copier | C12: 18839.69 | D12: 6983.88 | E12: =IF(C12=0,0,D12/C12) | F12: 38
A13: 8 | B13: HP Designjet T520 Inkjet Large Format Printer - 24" Color | C13: 18374.9 | D13: 4094.98 | E13: =IF(C13=0,0,D13/C13) | F13: 12
A14: 9 | B14: GBC DocuBind P400 Electric Binding System | C14: 17965.07 | D14: -1878.17 | E14: =IF(C14=0,0,D14/C14) | F14: 27
A15: 10 | B15: High Speed Automatic Electric Letter Opener | C15: 17030.31 | D15: -262 | E15: =IF(C15=0,0,D15/C15) | F15: 11
A16: 11 | B16: Lexmark MX611dhe Monochrome Laser Printer | C16: 16829.9 | D16: -4589.97 | E16: =IF(C16=0,0,D16/C16) | F16: 18
A17: 12 | B17: Martin Yale Chadless Opener Electric Letter Opener | C17: 16656.2 | D17: -1299.18 | E17: =IF(C17=0,0,D17/C17) | F17: 22
... A25: 20 | B25: Canon PC1060 Personal Laser Copier | C25: 11619.83 | D25: 4570.93 | E25: =IF(C25=0,0,D25/C25) | F25: 19
A28: Top 10 Loss-Making Products
A30: Rank | B30: Product Name | C30: Total Sales | D30: Total Profit | E30: Profit Margin | F30: Units Sold
A31: 1 | B31: Cubify CubeX 3D Printer Double Head Print | C31: 11099.96 | D31: -8879.97 | E31: =IF(C31=0,0,D31/C31) | F31: 9
A32: 2 | B32: Lexmark MX611dhe Monochrome Laser Printer | C32: 16829.9 | D32: -4589.97 | E32: =IF(C32=0,0,D32/C32) | F32: 18
A33: 3 | B33: Cubify CubeX 3D Printer Triple Head Print | C33: 7999.98 | D33: -3839.99 | E33: =IF(C33=0,0,D33/C33) | F33: 4
A34: 4 | B34: Chromcraft Bull-Nose Wood Oval Conference Tables & Bases | C34: 9917.64 | D34: -2876.12 | E34: =IF(C34=0,0,D34/C34) | F34: 27
A35: 5 | B35: Bush Advantage Collection Racetrack Conference Table | C35: 9544.73 | D35: -1934.4 | E35: =IF(C35=0,0,D35/C35) | F35: 33
A36: 6 | B36: GBC DocuBind P400 Electric Binding System | C36: 17965.07 | D36: -1878.17 | E36: =IF(C36=0,0,D36/C36) | F36: 27
A37: 7 | B37: Cisco TelePresence System EX90 Videoconferencing Unit | C37: 22638.48 | D37: -1811.08 | E37: =IF(C37=0,0,D37/C37) | F37: 6
A38: 8 | B38: Martin Yale Chadless Opener Electric Letter Opener | C38: 16656.2 | D38: -1299.18 | E38: =IF(C38=0,0,D38/C38) | F38: 22
A39: 9 | B39: Balt Solid Wood Round Tables | C39: 6518.75 | D39: -1201.06 | E39: =IF(C39=0,0,D39/C39) | F39: 19
A40: 10 | B40: BoxOffice By Design Rectangular and Half-Moon Meeting Room Tables | C40: 1706.25 | D40: -1148.44 | E40: =IF(C40=0,0,D40/C40) | F40: 15
A43: ABC Analysis (Pareto 80/20 Rule)
A45: Class | B45: Product Count | C45: % of Products | D45: Total Sales | E45: % of Revenue
A46: A | B46: 419 | C46: 22.6 | D46: 1836737 | E46: =IF(SUM(D46:D48)=0,0,D46/SUM(D46:D48))
A47: B | B47: 490 | C47: 26.5 | D47: 345324.25 | E47: =IF(SUM(D46:D48)=0,0,D47/SUM(D46:D48))
A48: C | B48: 941 | C48: 50.9 | D48: 115139.57 | E48: =IF(SUM(D46:D48)=0,0,D48/SUM(D46:D48))

Sheet Regional Analysis
A1: Regional Sales & Profit Analysis
A3: Region | B3: Total Sales | C3: Total Profit | D3: Profit Margin | E3: Order Count | F3: Avg Order Value
A4: West | B4: =SUMIF('Raw Data'!M2:M9995,A4,'Raw Data'!Q2:Q9995) | C4: =SUMIF('Raw Data'!M2:M9995,A4,'Raw Data'!T2:T9995) | D4: =IF(B4=0,0,C4/B4) | E4: =COUNTIF('Raw Data'!M2:M9995,A4) | F4: =IF(E4=0,0,B4/E4)
A5: East | B5: =SUMIF('Raw Data'!M2:M9995,A5,'Raw Data'!Q2:Q9995) | C5: =SUMIF('Raw Data'!M2:M9995,A5,'Raw Data'!T2:T9995) | D5: =IF(B5=0,0,C5/B5) | E5: =COUNTIF('Raw Data'!M2:M9995,A5) | F5: =IF(E5=0,0,B5/E5)
A6: Central | B6: =SUMIF('Raw Data'!M2:M9995,A6,'Raw Data'!Q2:Q9995) | C6: =SUMIF('Raw Data'!M2:M9995,A6,'Raw Data'!T2:T9995) | D6: =IF(B6=0,0,C6/B6) | E6: =COUNTIF('Raw Data'!M2:M9995,A6) | F6: =IF(E6=0,0,B6/E6)
A7: South | B7: =SUMIF('Raw Data'!M2:M9995,A7,'Raw Data'!Q2:Q9995) | C7: =SUMIF('Raw Data'!M2:M9995,A7,'Raw Data'!T2:T9995) | D7: =IF(B7=0,0,C7/B7) | E7: =COUNTIF('Raw Data'!M2:M9995,A7) | F7: =IF(E7=0,0,B7/E7)
A8: TOTAL | B8: =SUM(B4:B7) | C8: =SUM(C4:C7) | D8: =IF(B8=0,0,C8/B8) | E8: =SUM(E4:E7) | F8: =IF(E8=0,0,B8/E8)
A39: Top 15 States by Revenue
A41: Rank | B41: State | C41: Total Sales | D41: Total Profit | E41: Profit Margin | F41: Orders
A42: 1 | B42: California | C42: 457687.63 | D42: 76381.39 | E42: =IF(C42=0,0,D42/C42) | F42: 1021
A43: 2 | B43: New York | C43: 310876.27 | D43: 74038.55 | E43: =IF(C43=0,0,D43/C43) | F43: 562
A44: 3 | B44: Texas | C44: 170188.05 | D44: -25729.36 | E44: =IF(C44=0,0,D44/C44) | F44: 487
A45: 4 | B45: Washington | C45: 138641.27 | D45: 33402.65 | E45: =IF(C45=0,0,D45/C45) | F45: 256
A46: 5 | B46: Pennsylvania | C46: 116511.91 | D46: -15559.96 | E46: =IF(C46=0,0,D46/C46) | F46: 288
A47: 6 | B47: Florida | C47: 89473.71 | D47: -3399.3 | E47: =IF(C47=0,0,D47/C47) | F47: 200
A48: 7 | B48: Illinois | C48: 80166.1 | D48: -12607.89 | E48: =IF(C48=0,0,D48/C48) | F48: 276
A49: 8 | B49: Ohio | C49: 78258.14 | D49: -16971.38 | E49: =IF(C49=0,0,D49/C49) | F49: 236
A50: 9 | B50: Michigan | C50: 76269.61 | D50: 24463.19 | E50: =IF(C50=0,0,D50/C50) | F50: 117
A51: 10 | B51: Virginia | C51: 70636.72 | D51: 18597.95 | E51: =IF(C51=0,0,D51/C51) | F51: 115
A52: 11 | B52: North Carolina | C52: 55603.16 | D52: -7490.91 | E52: =IF(C52=0,0,D52/C52) | F52: 136
A53: 12 | B53: Indiana | C53: 53555.36 | D53: 18382.94 | E53: =IF(C53=0,0,D53/C53) | F53: 73
... A56: 15 | B56: New Jersey | C56: 35764.31 | D56: 9772.91 | E56: =IF(C56=0,0,D56/C56) | F56: 61

Sheet Time Series Analysis
A1: Time Series & Seasonality Analysis
A3: Period | B3: Revenue | C3: 3-Month MA | D3: 6-Month MA | E3: MoM Growth
A4: 2014-01 | B4: 14236.9
A5: 2014-02 | B5: 4519.89 | E5: =IF(B4=0,0,(B5-B4)/B4)
A6: 2014-03 | B6: 55691.01 | C6: =AVERAGE(B4:B6) | E6: =IF(B5=0,0,(B6-B5)/B5)
A7: 2014-04 | B7: 28295.35 | C7: =AVERAGE(B5:B7) | E7: =IF(B6=0,0,(B7-B6)/B6)
A8: 2014-05 | B8: 23648.29 | C8: =AVERAGE(B6:B8) | E8: =IF(B7=0,0,(B8-B7)/B7)
A9: 2014-06 | B9: 34595.13 | C9: =AVERAGE(B7:B9) | D9: =AVERAGE(B4:B9) | E9: =IF(B8=0,0,(B9-B8)/B8)
A10: 2014-07 | B10: 33946.39 | C10: =AVERAGE(B8:B10) | D10: =AVERAGE(B5:B10) | E10: =IF(B9=0,0,(B10-B9)/B9)
A11: 2014-08 | B11: 27909.47 | C11: =AVERAGE(B9:B11) | D11: =AVERAGE(B6:B11) | E11: =IF(B10=0,0,(B11-B10)/B10)
A12: 2014-09 | B12: 81777.35 | C12: =AVERAGE(B10:B12) | D12: =AVERAGE(B7:B12) | E12: =IF(B11=0,0,(B12-B11)/B11)
A13: 2014-10 | B13: 31453.39 | C13: =AVERAGE(B11:B13) | D13: =AVERAGE(B8:B13) | E13: =IF(B12=0,0,(B13-B12)/B12)
A14: 2014-11 | B14: 78628.72 | C14: =AVERAGE(B12:B14) | D14: =AVERAGE(B9:B14) | E14: =IF(B13=0,0,(B14-B13)/B13)
A15: 2014-12 | B15: 69545.62 | C15: =AVERAGE(B13:B15) | D15: =AVERAGE(B10:B15) | E15: =IF(B14=0,0,(B15-B14)/B14)
A16: 2015-01 | B16: 18174.08 | C16: =AVERAGE(B14:B16) | D16: =AVERAGE(B11:B16) | E16: =IF(B15=0,0,(B16-B15)/B15)
A17: 2015-02 | B17: 11951.41 | C17: =AVERAGE(B15:B17) | D17: =AVERAGE(B12:B17) | E17: =IF(B16=0,0,(B17-B16)/B16)
A18: 2015-03 | B18: 38726.25 | C18: =AVERAGE(B16:B18) | D18: =AVERAGE(B13:B18) | E18: =IF(B17=0,0,(B18-B17)/B17)
A19: 2015-04 | B19: 34195.21 | C19: =AVERAGE(B17:B19) | D19: =AVERAGE(B14:B19) | E19: =IF(B18=0,0,(B19-B18)/B18)
A20: 2015-05 | B20: 30131.69 | C20: =AVERAGE(B18:B20) | D20: =AVERAGE(B15:B20) | E20: =IF(B19=0,0,(B20-B19)/B19)
... A51: 2017-12 | B51: 83829.32 | C51: =AVERAGE(B49:B51) | D51: =AVERAGE(B46:B51) | E51: =IF(B50=0,0,(B51-B50)/B50)
A85: Seasonality Analysis (Avg Monthly Revenue)
A87: Month | B87: Month Name | C87: Avg Revenue | D87: Seasonality Index
A88: 1 | B88: Jan | C88: 249.15 | D88: =IF(AVERAGE(C88:C99)=0,0,C88/AVERAGE(C88:C99))
A89: 2 | B89: Feb | C89: 199.17 | D89: =IF(AVERAGE(C88:C99)=0,0,C89/AVERAGE(C88:C99))
A90: 3 | B90: Mar | C90: 294.55 | D90: =IF(AVERAGE(C88:C99)=0,0,C90/AVERAGE(C88:C99))
A91: 4 | B91: Apr | C91: 206.23 | D91: =IF(AVERAGE(C88:C99)=0,0,C91/AVERAGE(C88:C99))
A92: 5 | B92: May | C92: 210.92 | D92: =IF(AVERAGE(C88:C99)=0,0,C92/AVERAGE(C88:C99))
A93: 6 | B93: Jun | C93: 213 | D93: =IF(AVERAGE(C88:C99)=0,0,C93/AVERAGE(C88:C99))
A94: 7 | B94: Jul | C94: 207.38 | D94: =IF(AVERAGE(C88:C99)=0,0,C94/AVERAGE(C88:C99))
A95: 8 | B95: Aug | C95: 225.27 | D95: =IF(AVERAGE(C88:C99)=0,0,C95/AVERAGE(C88:C99))
A96: 9 | B96: Sep | C96: 222.45 | D96: =IF(AVERAGE(C88:C99)=0,0,C96/AVERAGE(C88:C99))
A97: 10 | B97: Oct | C97: 244.59 | D97: =IF(AVERAGE(C88:C99)=0,0,C97/AVERAGE(C88:C99))
A98: 11 | B98: Nov | C98: 239.61 | D98: =IF(AVERAGE(C88:C99)=0,0,C98/AVERAGE(C88:C99))
A99: 12 | B99: Dec | C99: 231.03 | D99: =IF(AVERAGE(C88:C99)=0,0,C99/AVERAGE(C88:C99))

Sheet Shipping Analysis
A1: Shipping & Delivery Analysis
A3: Ship Mode | B3: Total Sales | C3: Total Profit | D3: Profit Margin | E3: Order Count | F3: % of Orders | G3: Avg Delivery Days
A4: Standard Class | B4: =SUMIF('Raw Data'!E2:E9995,A4,'Raw Data'!Q2:Q9995) | C4: =SUMIF('Raw Data'!E2:E9995,A4,'Raw Data'!T2:T9995) | D4: =IF(B4=0,0,C4/B4) | E4: =COUNTIF('Raw Data'!E2:E9995,A4) | F4: =IF(SUM(E4:E7)=0,0,E4/SUM(E4:E7)) | G4: =AVERAGEIF('Raw Data'!E2:E9995,A4,'Raw Data'!U2:U9995)
A5: Second Class | B5: =SUMIF('Raw Data'!E2:E9995,A5,'Raw Data'!Q2:Q9995) | C5: =SUMIF('Raw Data'!E2:E9995,A5,'Raw Data'!T2:T9995) | D5: =IF(B5=0,0,C5/B5) | E5: =COUNTIF('Raw Data'!E2:E9995,A5) | F5: =IF(SUM(E4:E7)=0,0,E5/SUM(E4:E7)) | G5: =AVERAGEIF('Raw Data'!E2:E9995,A5,'Raw Data'!U2:U9995)
A6: First Class | B6: =SUMIF('Raw Data'!E2:E9995,A6,'Raw Data'!Q2:Q9995) | C6: =SUMIF('Raw Data'!E2:E9995,A6,'Raw Data'!T2:T9995) | D6: =IF(B6=0,0,C6/B6) | E6: =COUNTIF('Raw Data'!E2:E9995,A6) | F6: =IF(SUM(E4:E7)=0,0,E6/SUM(E4:E7)) | G6: =AVERAGEIF('Raw Data'!E2:E9995,A6,'Raw Data'!U2:U9995)
A7: Same Day | B7: =SUMIF('Raw Data'!E2:E9995,A7,'Raw Data'!Q2:Q9995) | C7: =SUMIF('Raw Data'!E2:E9995,A7,'Raw Data'!T2:T9995) | D7: =IF(B7=0,0,C7/B7) | E7: =COUNTIF('Raw Data'!E2:E9995,A7) | F7: =IF(SUM(E4:E7)=0,0,E7/SUM(E4:E7)) | G7: =AVERAGEIF('Raw Data'!E2:E9995,A7,'Raw Data'!U2:U9995)
A8: TOTAL | B8: =SUM(B4:B7) | C8: =SUM(C4:C7) | D8: =IF(B8=0,0,C8/B8) | E8: =SUM(E4:E7) | G8: =AVERAGE('Raw Data'!U2:U9995)
A36: Delivery Time Distribution
A38: Delivery Window | B38: Order Count | C38: % of Total
A39: 0-2 days | B39: 1703 | C39: =IF(SUM(B39:B43)=0,0,B39/SUM(B39:B43))
A40: 3-4 days | B40: 3779 | C40: =IF(SUM(B39:B43)=0,0,B40/SUM(B39:B43))
A41: 5-6 days | B41: 3372 | C41: =IF(SUM(B39:B43)=0,0,B41/SUM(B39:B43))
A42: 7-8 days | B42: 621 | C42: =IF(SUM(B39:B43)=0,0,B42/SUM(B39:B43))
A43: 8+ days | B43: 0 | C43: =IF(SUM(B39:B43)=0,0,B43/SUM(B39:B43))

Sheet Discount Impact
A1: Discount Impact on Profitability
A3: Discount Band | B3: Order Count | C3: % of Orders | D3: Total Sales | E3: Total Profit | F3: Avg Profit/Order | G3: Profit Margin
A4: No Discount | B4: 4798 | C4: =IF(SUM(B4:B9)=0,0,B4/SUM(B4:B9)) | D4: 1087908.5 | E4: 320987.6 | F4: =IF(B4=0,0,E4/B4) | G4: =IF(D4=0,0,E4/D4)
A5: 1-10% | B5: 94 | C5: =IF(SUM(B4:B9)=0,0,B5/SUM(B4:B9)) | D5: 54369.35 | E5: 9029.18 | F5: =IF(B5=0,0,E5/B5) | G5: =IF(D5=0,0,E5/D5)
A6: 11-20% | B6: 3709 | C6: =IF(SUM(B4:B9)=0,0,B6/SUM(B4:B9)) | D6: 792152.89 | E6: 91756.3 | F6: =IF(B6=0,0,E6/B6) | G6: =IF(D6=0,0,E6/D6)
A7: 21-30% | B7: 227 | C7: =IF(SUM(B4:B9)=0,0,B7/SUM(B4:B9)) | D7: 103226.65 | E7: -10369.28 | F7: =IF(B7=0,0,E7/B7) | G7: =IF(D7=0,0,E7/D7)
A8: 31-50% | B8: 310 | C8: =IF(SUM(B4:B9)=0,0,B8/SUM(B4:B9)) | D8: 195314.76 | E8: -48447.73 | F8: =IF(B8=0,0,E8/B8) | G8: =IF(D8=0,0,E8/D8)
A9: 50%+ | B9: 856 | C9: =IF(SUM(B4:B9)=0,0,B9/SUM(B4:B9)) | D9: 64228.74 | E9: -76559.05 | F9: =IF(B9=0,0,E9/B9) | G9: =IF(D9=0,0,E9/D9)
A40: Discount Impact by Category
A42: Category | B42: Discount Band | C42: Total Sales | D42: Total Profit | E42: Profit Margin
A43: Furniture | B43: No Discount | C43: 256025.27 | D43: 58133.08 | E43: =IF(C43=0,0,D43/C43)
A44: Furniture | B44: 1-10% | C44: 46634.25 | D44: 7111.01 | E44: =IF(C44=0,0,D44/C44)
A45: Furniture | B45: 11-20% | C45: 244189.54 | D45: 7684.94 | E45: =IF(C45=0,0,D45/C45)
A46: Furniture | B46: 21-30% | C46: 99470.35 | D46: -10695.32 | E46: =IF(C46=0,0,D46/C46)
A47: Furniture | B47: 31-50% | C47: 86576.31 | D47: -33942.84 | E47: =IF(C47=0,0,D47/C47)
A48: Furniture | B48: 50%+ | C48: 9104.08 | D48: -9839.59 | E48: =IF(C48=0,0,D48/C48)
A49: Office Supplies | B49: No Discount | C49: 442150 | D49: 130506.11 | E49: =IF(C49=0,0,D49/C49)
A50: Office Supplies | B50: 1-10% | C50: 4324.15 | D50: 1086.08 | E50: =IF(C50=0,0,D50/C50)
A51: Office Supplies | B51: 11-20% | C51: 233049.74 | D51: 38038.75 | E51: =IF(C51=0,0,D51/C51)
A52: Office Supplies | B52: 50%+ | C52: 39523.15 | D52: -47140.14 | E52: =IF(C52=0,0,D52/C52)
A53: Technology | B53: No Discount | C53: 389733.2 | D53: 132348.42 | E53: =IF(C53=0,0,D53/C53)
A54: Technology | B54: 1-10% | C54: 3410.95 | D54: 832.08 | E54: =IF(C54=0,0,D54/C54)
... A58: Technology | B58: 50%+ | C58: 15601.51 | D58: -19579.32 | E58: =IF(C58=0,0,D58/C58)

Sheet KPI Dashboard
A1: Executive KPI Dashboard
A2: Data Period: Jan 2014 - Dec 2017
A4: Total Revenue | D4: Total Profit | G4: Profit Margin
A5: =SUM('Raw Data'!Q2:Q9995) | D5: =SUM('Raw Data'!T2:T9995) | G5: =SUM('Raw Data'!T2:T9995)/SUM('Raw Data'!Q2:Q9995)
A7: Total Orders | D7: Total Units Sold | G7: Avg Order Value
A8: =COUNTA('Raw Data'!B2:B9995) | D8: =SUM('Raw Data'!R2:R9995) | G8: =SUM('Raw Data'!Q2:Q9995)/COUNTA('Raw Data'!B2:B9995)
A10: Avg Profit/Order | D10: Avg Discount | G10: Avg Delivery Days
A11: =SUM('Raw Data'!T2:T9995)/COUNTA('Raw Data'!B2:B9995) | D11: =AVERAGE('Raw Data'!S2:S9995) | G11: =AVERAGE('Raw Data'!U2:U9995)
A16: Category Performance
A18: Category | B18: Revenue | C18: Profit | D18: Margin | E18: Orders | F18: % of Revenue
A19: Technology | B19: =SUMIF('Raw Data'!N2:N9995,A19,'Raw Data'!Q2:Q9995) | C19: =SUMIF('Raw Data'!N2:N9995,A19,'Raw Data'!T2:T9995) | D19: =IF(B19=0,0,C19/B19) | E19: =COUNTIF('Raw Data'!N2:N9995,A19) | F19: =IF(SUM('Raw Data'!Q2:Q9995)=0,0,B19/SUM('Raw Data'!Q2:Q9995))
A20: Furniture | B20: =SUMIF('Raw Data'!N2:N9995,A20,'Raw Data'!Q2:Q9995) | C20: =SUMIF('Raw Data'!N2:N9995,A20,'Raw Data'!T2:T9995) | D20: =IF(B20=0,0,C20/B20) | E20: =COUNTIF('Raw Data'!N2:N9995,A20) | F20: =IF(SUM('Raw Data'!Q2:Q9995)=0,0,B20/SUM('Raw Data'!Q2:Q9995))
A21: Office Supplies | B21: =SUMIF('Raw Data'!N2:N9995,A21,'Raw Data'!Q2:Q9995) | C21: =SUMIF('Raw Data'!N2:N9995,A21,'Raw Data'!T2:T9995) | D21: =IF(B21=0,0,C21/B21) | E21: =COUNTIF('Raw Data'!N2:N9995,A21) | F21: =IF(SUM('Raw Data'!Q2:Q9995)=0,0,B21/SUM('Raw Data'!Q2:Q9995))
A24: Regional Performance
A26: Region | B26: Revenue | C26: Profit | D26: Margin | E26: Orders | F26: % of Revenue
A27: West | B27: =SUMIF('Raw Data'!M2:M9995,A27,'Raw Data'!Q2:Q9995) | C27: =SUMIF('Raw Data'!M2:M9995,A27,'Raw Data'!T2:T9995) | D27: =IF(B27=0,0,C27/B27) | E27: =COUNTIF('Raw Data'!M2:M9995,A27) | F27: =IF(SUM('Raw Data'!Q2:Q9995)=0,0,B27/SUM('Raw Data'!Q2:Q9995))
A28: East | B28: =SUMIF('Raw Data'!M2:M9995,A28,'Raw Data'!Q2:Q9995) | C28: =SUMIF('Raw Data'!M2:M9995,A28,'Raw Data'!T2:T9995) | D28: =IF(B28=0,0,C28/B28) | E28: =COUNTIF('Raw Data'!M2:M9995,A28) | F28: =IF(SUM('Raw Data'!Q2:Q9995)=0,0,B28/SUM('Raw Data'!Q2:Q9995))
A29: Central | B29: =SUMIF('Raw Data'!M2:M9995,A29,'Raw Data'!Q2:Q9995) | C29: =SUMIF('Raw Data'!M2:M9995,A29,'Raw Data'!T2:T9995) | D29: =IF(B29=0,0,C29/B29) | E29: =COUNTIF('Raw Data'!M2:M9995,A29) | F29: =IF(SUM('Raw Data'!Q2:Q9995)=0,0,B29/SUM('Raw Data'!Q2:Q9995))
A30: South | B30: =SUMIF('Raw Data'!M2:M9995,A30,'Raw Data'!Q2:Q9995) | C30: =SUMIF('Raw Data'!M2:M9995,A30,'Raw Data'!T2:T9995) | D30: =IF(B30=0,0,C30/B30) | E30: =COUNTIF('Raw Data'!M2:M9995,A30) | F30: =IF(SUM('Raw Data'!Q2:Q9995)=0,0,B30/SUM('Raw Data'!Q2:Q9995))

Sheet Cohort Analysis
A1: Customer Cohort Retention Analysis
A3: Quarterly Cohort Retention (%)
A5: Cohort Quarter | B5: New Customers | C5: Month 0 | D5: Month 3 | E5: Month 6 | F5: Month 9 | G5: Month 12 | H5: Month 18 | I5: Month 24
A6: 2014 Q1 | B6: 121 | C6: 100 | D6: 7.6 | E6: 8.5 | F6: 11.8 | G6: 9.3 | H6: 11.6 | I6: 9.3
A7: 2014 Q2 | B7: 160 | C7: 100 | D7: 7.5 | E7: 16.3 | F7: 6.5 | G7: 8 | H7: 14.6 | I7: 10.6
A8: 2014 Q3 | B8: 161 | C8: 100 | D8: 19.3 | E8: 8.6 | F8: 4.5 | G8: 11 | H8: 6.6 | I8: 15
A9: 2014 Q4 | B9: 153 | C9: 100 | D9: 5.1 | E9: 7.8 | F9: 12 | G9: 16.3 | H9: 11.3 | I9: 19.1
A10: 2015 Q1 | B10: 32 | C10: 100 | D10: 16.7 | E10: 22.6 | F10: 9.9 | G10: 11.4 | H10: 38.9 | I10: 5.6
A11: 2015 Q2 | B11: 36 | C11: 100 | D11: 19.4 | E11: 19.4 | F11: 16.7 | G11: 25 | H11: 13.9 | I11: 8.3
A12: 2015 Q3 | B12: 36 | C12: 100 | D12: 16 | E12: 18.8 | F12: 8.3 | G12: 15.6 | H12: 15.3 | I12: 26
A13: 2015 Q4 | B13: 32 | C13: 100 | D13: 7.7 | E13: 10 | F13: 14.7 | G13: 8.8 | H13: 20.5 | I13: 28.1
A14: 2016 Q1 | B14: 14 | C14: 100 | D14: 16.7 | E14: 16.7 | F14: 27.8 | G14: 16.7 | H14: 33.3
A15: 2016 Q2 | B15: 22 | C15: 100 | D15: 26.8 | E15: 20.5 | F15: 22.6 | G15: 17.9 | H15: 26.8
A16: 2016 Q3 | B16: 6 | C16: 100 | F16: 50
A17: 2016 Q4 | B17: 9 | C17: 100 | F17: 16.7 | G17: 61.1
A18: 2017 Q1 | B18: 3 | C18: 100 | D18: 33.3
A19: 2017 Q2 | B19: 2 | C19: 100 | E19: 100
A20: 2017 Q3 | B20: 3 | C20: 100
A21: 2017 Q4 | B21: 3 | C21: 100
A24: Revenue by Customer Cohort Quarter
A26: Cohort Quarter | B26: Total Revenue | C26: Avg Revenue/Customer | D26: Customer Count
A27: 2014 Q1 | B27: 405717.97 | C27: =IF(D27=0,0,B27/D27) | D27: 121
A28: 2014 Q2 | B28: 505496.26 | C28: =IF(D28=0,0,B28/D28) | D28: 160
A29: 2014 Q3 | B29: 481595.84 | C29: =IF(D29=0,0,B29/D29) | D29: 161
A30: 2014 Q4 | B30: 444514.53 | C30: =IF(D30=0,0,B30/D30) | D30: 153
A31: 2015 Q1 | B31: 89201.01 | C31: =IF(D31=0,0,B31/D31) | D31: 32
A32: 2015 Q2 | B32: 101781.64 | C32: =IF(D32=0,0,B32/D32) | D32: 36
A33: 2015 Q3 | B33: 85074.59 | C33: =IF(D33=0,0,B33/D33) | D33: 36
A34: 2015 Q4 | B34: 60597.32 | C34: =IF(D34=0,0,B34/D34) | D34: 32
A35: 2016 Q1 | B35: 33511.31 | C35: =IF(D35=0,0,B35/D35) | D35: 14
A36: 2016 Q2 | B36: 63361.47 | C36: =IF(D36=0,0,B36/D36) | D36: 22
A37: 2016 Q3 | B37: 8535.6 | C37: =IF(D37=0,0,B37/D37) | D37: 6
A38: 2016 Q4 | B38: 10301.5 | C38: =IF(D38=0,0,B38/D38) | D38: 9
... A42: 2017 Q4 | B42: 2799.11 | C42: =IF(D42=0,0,B42/D42) | D42: 3
